asl/__init__.py
asl/__main__.py
asl/_asl.cpython-37m-darwin.so
asl/_constants.py
asl-1.1.dist-info/METADATA
asl-1.1.dist-info/WHEEL
asl-1.1.dist-info/top_level.txt
asl-1.1.dist-info/RECORD
