Metadata-Version: 2.1
Name: asl
Version: 1.1
Summary: Bindings to the ASL library on Mac OS X
Home-page: http://asl.readthedocs.io/
Author: Ronald Oussoren
Author-email: ronaldoussoren@mac.com
Maintainer: Ronald Oussoren
Maintainer-email: ronaldoussoren@mac.com
License: MIT
Download-URL: http://pypi.python.org/pypi/asl
Keywords: logging
Platform: Mac
Platform: OS
Platform: X
Classifier: Intended Audience :: Developers
Classifier: Intended Audience :: System Administrators
Classifier: License :: OSI Approved :: MIT License
Classifier: Programming Language :: Python
Classifier: Programming Language :: Python :: 3
Classifier: Programming Language :: Python :: 3.6
Classifier: Programming Language :: Python :: 3.7
Classifier: Programming Language :: Python :: 3.8
Classifier: Environment :: MacOS X
Classifier: Operating System :: MacOS :: MacOS X
Classifier: Topic :: Software Development :: Libraries :: Python Modules
Classifier: Topic :: System :: Logging
Classifier: Development Status :: 5 - Production/Stable
Project-URL: Documentation, https://asl.readthedocs.io/en/latest/
Project-URL: Issue tracker, https://github.com/ronaldoussoren/asl/issues
Project-URL: Repository, https://github.com/ronaldoussoren/asl
